[
    {
        "_id": 1,
        "name": "Egg",
        "price": "$6",
        "description": "Simple boiled eggs enhanced with a home-made spice paste and a crackling tempering. This egg masala can be a great option for dinner parties or even a casual lunch. This is a quick and super easy egg recipe. Just pair with chapati or paratha and devour a delicious meal.",
        "quantity": "5",
        "supliar": "Henry Roycek",
        "img": "https://i.ibb.co/XDBMbWz/egg3.jpg"
    },
    {
        "_id": 9,
        "name": "Chicken",
        "price": "$6",
        "description": "For a juicier Masala Chicken, marinate the chicken for a good 30 minutes to one hour in 1 tsp turmeric powder, 2 tbsp mustrad oil, salt and 2 tsp curd and garlic paste. Fresh tomatoes always works better than tomato puree. ",
        "quantity": "9",
        "supliar": "Adolf Hitler",
        "img": "https://i.ibb.co/n8dHKk0/chiken1.jpg"
    },
    {
        "_id": 11,
        "name": "Biryani",
        "price": "$36",
        "description": "Biryani is a mixed rice dish originating among the royal khansamas of the durbar of Old Delhi, under the Mughal Empire, during the late 16th century of the erstwhile Mughal Court.",
        "quantity": "67",
        "supliar": "Yoshisuke Aikawa ",
        "img": "https://i.ibb.co/DGrcmr5/b2.jpg"
    },
    {
        "_id": 11,
        "name": "Sandwich",
        "price": "$6",
        "description": "Sandwich Recipes- They are delicious, they are easy and they are your saviors in the times of deep hunger and low bank of ingredients and will to cook. We are talking about the good old sandwich, you can make it as simple as you want or get creative and spruce it up with the most exotic ingredients in town",
        "quantity": "67",
        "supliar": "Yoshisuke Aikawa ",
        "img": "https://i.ibb.co/P9X4V1r/san4.jpg"
    },
    {
        "_id": 2,
        "name": "Egg",
        "price": "$2",
        "description": "Simple boiled eggs enhanced with a home-made spice paste and a crackling tempering. This egg masala can be a great option for dinner parties or even a casual lunch. This is a quick and super easy egg recipe. Just pair with chapati or paratha and devour a delicious meal.",
        "quantity": "58",
        "supliar": "Soichiro Honda",
        "img": "https://i.ibb.co/K72WgJD/egg4.jpg"
    },
    {
        "_id": 3,
        "name": "Egg",
        "price": "$4",
        "description": "Simple boiled eggs enhanced with a home-made spice paste and a crackling tempering. This egg masala can be a great option for dinner parties or even a casual lunch. This is a quick and super easy egg recipe. Just pair with chapati or paratha and devour a delicious meal.",
        "quantity": "34",
        "supliar": "Bayerische Motoren Werke GmnH",
        "img": "https://i.ibb.co/bPyKbMJ/egg5.jpg"
    },
    {
        "_id": 4,
        "name": "Egg",
        "price": "$2",
        "description": "Simple boiled eggs enhanced with a home-made spice paste and a crackling tempering. This egg masala can be a great option for dinner parties or even a casual lunch. This is a quick and super easy egg recipe. Just pair with chapati or paratha and devour a delicious meal.",
        "quantity": "11",
        "supliar": "Enzo Ferrari",
        "img": "https://i.ibb.co/K5J2LmK/egg1.jpg "
    },
    {
        "_id": 5,
        "name": "Egg",
        "price": "$1",
        "description": "Simple boiled eggs enhanced with a home-made spice paste and a crackling tempering. This egg masala can be a great option for dinner parties or even a casual lunch. This is a quick and super easy egg recipe. Just pair with chapati or paratha and devour a delicious meal.",
        "quantity": "33",
        "supliar": "Antoine Laumet de La Mothe",
        "img": "https://i.ibb.co/DMdq38s/egg2.jpg "
    },
    {
        "_id": 6,
        "name": "Chicken",
        "price": "$3",
        "description": "For a juicier Masala Chicken, marinate the chicken for a good 30 minutes to one hour in 1 tsp turmeric powder, 2 tbsp mustrad oil, salt and 2 tsp curd and garlic paste. Fresh tomatoes always works better than tomato puree. ",
        "quantity": "15",
        "supliar": "August Horch",
        "img": "https://i.ibb.co/9WfhZ1B/chiken2.jpg"
    },
    {
        "_id": 10,
        "name": "Chicken",
        "price": "$9",
        "description": "For a juicier Masala Chicken, marinate the chicken for a good 30 minutes to one hour in 1 tsp turmeric powder, 2 tbsp mustrad oil, salt and 2 tsp curd and garlic paste. Fresh tomatoes always works better than tomato puree. ",
        "quantity": "16",
        "supliar": "Henry Ford ",
        "img": "https://i.ibb.co/WnGHzNM/chiken4.jpg"
    },
    {
        "_id": 11,
        "name": "Chicken",
        "price": "$6",
        "description": "For a juicier Masala Chicken, marinate the chicken for a good 30 minutes to one hour in 1 tsp turmeric powder, 2 tbsp mustrad oil, salt and 2 tsp curd and garlic paste. Fresh tomatoes always works better than tomato puree. ",
        "quantity": "67",
        "supliar": "Yoshisuke Aikawa ",
        "img": "https://i.ibb.co/SdXJ7mM/chiken3.jpg"
    },
    {
        "_id": 11,
        "name": "Sandwich",
        "price": "$3",
        "description": "Sandwich Recipes- They are delicious, they are easy and they are your saviors in the times of deep hunger and low bank of ingredients and will to cook. We are talking about the good old sandwich, you can make it as simple as you want or get creative and spruce it up with the most exotic ingredients in town",
        "quantity": "67",
        "supliar": "Yoshisuke Aikawa ",
        "img": "https://i.ibb.co/Z8y4mD0/san1.jpg"
    },
    {
        "_id": 11,
        "name": "Sandwich",
        "price": "$2",
        "description": "Sandwich Recipes- They are delicious, they are easy and they are your saviors in the times of deep hunger and low bank of ingredients and will to cook. We are talking about the good old sandwich, you can make it as simple as you want or get creative and spruce it up with the most exotic ingredients in town",
        "quantity": "67",
        "supliar": "Yoshisuke Aikawa ",
        "img": "https://i.ibb.co/kmZPCzb/san2.jpg"
    },
    {
        "_id": 11,
        "name": "Sandwich",
        "price": "$3",
        "description": "Sandwich Recipes- They are delicious, they are easy and they are your saviors in the times of deep hunger and low bank of ingredients and will to cook. We are talking about the good old sandwich, you can make it as simple as you want or get creative and spruce it up with the most exotic ingredients in town",
        "quantity": "67",
        "supliar": "Yoshisuke Aikawa ",
        "img": "https://i.ibb.co/kmZPCzb/san5.jpg"
    },
    {
        "_id": 11,
        "name": "Sandwich",
        "price": "$6",
        "description": "Sandwich Recipes- They are delicious, they are easy and they are your saviors in the times of deep hunger and low bank of ingredients and will to cook. We are talking about the good old sandwich, you can make it as simple as you want or get creative and spruce it up with the most exotic ingredients in town",
        "quantity": "67",
        "supliar": "Yoshisuke Aikawa ",
        "img": "https://i.ibb.co/KVvmjMH/san3.png"
    },
    {
        "_id": 11,
        "name": "Biryani",
        "price": "$2",
        "description": "Biryani is a mixed rice dish originating among the royal khansamas of the durbar of Old Delhi, under the Mughal Empire, during the late 16th century of the erstwhile Mughal Court.",
        "quantity": "67",
        "supliar": "Yoshisuke Aikawa ",
        "img": "https://i.ibb.co/VLCWvqP/b4.jpg"
    },
    {
        "_id": 11,
        "name": "Biryani",
        "price": "$3",
        "description": "Biryani is a mixed rice dish originating among the royal khansamas of the durbar of Old Delhi, under the Mughal Empire, during the late 16th century of the erstwhile Mughal Court.",
        "quantity": "67",
        "supliar": "Yoshisuke Aikawa ",
        "img": "https://i.ibb.co/f4s9bMy/b5.jpg"
    },
    {
        "_id": 11,
        "name": "Biryani",
        "price": "$6",
        "description": "Biryani is a mixed rice dish originating among the royal khansamas of the durbar of Old Delhi, under the Mughal Empire, during the late 16th century of the erstwhile Mughal Court.",
        "quantity": "67",
        "supliar": "Yoshisuke Aikawa ",
        "img": "https://i.ibb.co/4KJj00L/b1.jpg"
    },
    {
        "_id": 11,
        "name": "Biryani",
        "price": "$26",
        "description": "Biryani is a mixed rice dish originating among the royal khansamas of the durbar of Old Delhi, under the Mughal Empire, during the late 16th century of the erstwhile Mughal Court.",
        "quantity": "67",
        "supliar": "Yoshisuke Aikawa ",
        "img": "https://i.ibb.co/dMvncCF/b3.jpg"
    }
]